pygments_dmdl-0.5.0-py3.6-nspkg.pth
dmdl/lexer.py
pygments_dmdl-0.5.0.dist-info/DESCRIPTION.rst
pygments_dmdl-0.5.0.dist-info/METADATA
pygments_dmdl-0.5.0.dist-info/RECORD
pygments_dmdl-0.5.0.dist-info/WHEEL
pygments_dmdl-0.5.0.dist-info/entry_points.txt
pygments_dmdl-0.5.0.dist-info/metadata.json
pygments_dmdl-0.5.0.dist-info/namespace_packages.txt
pygments_dmdl-0.5.0.dist-info/top_level.txt
