Metadata-Version: 2.0
Name: pygments-dmdl
Version: 0.5.0
Summary: DMDL lexer and highlighter for Pygments
Home-page: https://github.com/cocoatomo/pygments-dmdl
Author: cocoatomo
Author-email: cocoatomo77@gmail.com
License: Apache License (2.0)
Platform: UNKNOWN
Classifier: Development Status :: 4 - Beta
Classifier: License :: OSI Approved :: Apache Software License
Classifier: Programming Language :: Python
Classifier: Programming Language :: Python :: 2.7
Classifier: Programming Language :: Python :: 3.5
Classifier: Programming Language :: Python :: 3.6
Classifier: Topic :: Documentation
